mpesa_analysis/__init__.py
mpesa_analysis/analyzer.py
mpesa_analysis/main.py
mpesa_analysis/recommender.py
mpesa_analysis-0.1.0.dist-info/METADATA
mpesa_analysis-0.1.0.dist-info/WHEEL
mpesa_analysis-0.1.0.dist-info/top_level.txt
mpesa_analysis-0.1.0.dist-info/RECORD
